{
  "formatVersion": 1,
  "database": {
    "version": 4,
    "identityHash": "7466f9516e60f0843d795d8efa04743e",
    "entities": [
      {
        "tableName": "share_history",
        "createSql": "CREATE TABLE IF NOT EXISTS `${TABLE_NAME}` (`id` INTEGER PRIMARY KEY AUTOINCREMENT NOT NULL, `originalText` TEXT NOT NULL, `cleanedText` TEXT NOT NULL, `sharedAt` INTEGER NOT NULL, `notes` TEXT, `sync_id` TEXT NOT NULL, `updated_at` INTEGER NOT NULL, `source` TEXT NOT NULL)",
        "fields": [
          {
            "fieldPath": "id",
            "columnName": "id",
            "affinity": "INTEGER",
            "notNull": true
          },
          {
            "fieldPath": "originalText",
            "columnName": "originalText",
            "affinity": "TEXT",
            "notNull": true
          },
          {
            "fieldPath": "cleanedText",
            "columnName": "cleanedText",
            "affinity": "TEXT",
            "notNull": true
          },
          {
            "fieldPath": "sharedAt",
            "columnName": "sharedAt",
            "affinity": "INTEGER",
            "notNull": true
          },
          {
            "fieldPath": "notes",
            "columnName": "notes",
            "affinity": "TEXT"
          },
          {
            "fieldPath": "syncId",
            "columnName": "sync_id",
            "affinity": "TEXT",
            "notNull": true
          },
          {
            "fieldPath": "updatedAt",
            "columnName": "updated_at",
            "affinity": "INTEGER",
            "notNull": true
          },
          {
            "fieldPath": "source",
            "columnName": "source",
            "affinity": "TEXT",
            "notNull": true
          }
        ],
        "primaryKey": {
          "autoGenerate": true,
          "columnNames": [
            "id"
          ]
        }
      },
      {
        "tableName": "link_metadata",
        "createSql": "CREATE TABLE IF NOT EXISTS `${TABLE_NAME}` (`shareRecordId` INTEGER NOT NULL, `title` TEXT, `thumbnailUrl` TEXT, `description` TEXT, `articleSnippet` TEXT, `contentType` TEXT NOT NULL, `fetchStatus` TEXT NOT NULL, PRIMARY KEY(`shareRecordId`))",
        "fields": [
          {
            "fieldPath": "shareRecordId",
            "columnName": "shareRecordId",
            "affinity": "INTEGER",
            "notNull": true
          },
          {
            "fieldPath": "title",
            "columnName": "title",
            "affinity": "TEXT"
          },
          {
            "fieldPath": "thumbnailUrl",
            "columnName": "thumbnailUrl",
            "affinity": "TEXT"
          },
          {
            "fieldPath": "description",
            "columnName": "description",
            "affinity": "TEXT"
          },
          {
            "fieldPath": "articleSnippet",
            "columnName": "articleSnippet",
            "affinity": "TEXT"
          },
          {
            "fieldPath": "contentType",
            "columnName": "contentType",
            "affinity": "TEXT",
            "notNull": true
          },
          {
            "fieldPath": "fetchStatus",
            "columnName": "fetchStatus",
            "affinity": "TEXT",
            "notNull": true
          }
        ],
        "primaryKey": {
          "autoGenerate": false,
          "columnNames": [
            "shareRecordId"
          ]
        }
      }
    ],
    "setupQueries": [
      "CREATE TABLE IF NOT EXISTS room_master_table (id INTEGER PRIMARY KEY,identity_hash TEXT)",
      "INSERT OR REPLACE INTO room_master_table (id,identity_hash) VALUES(42, '7466f9516e60f0843d795d8efa04743e')"
    ]
  }
}